s3sync.py
pys3nfssync-0.0.1.dist-info/LICENSE
pys3nfssync-0.0.1.dist-info/METADATA
pys3nfssync-0.0.1.dist-info/WHEEL
pys3nfssync-0.0.1.dist-info/entry_points.txt
pys3nfssync-0.0.1.dist-info/top_level.txt
pys3nfssync-0.0.1.dist-info/RECORD
