Metadata-Version: 2.1
Name: pys3nfssync
Version: 0.0.1
Summary: Continuously Sync local files to/from S3
Home-page: https://github.com/srajput1991/s3sync
Author: Sachin Rajput
Author-email: er.sachinrajput1991@gmail.com
License: MIT
Platform: UNKNOWN
Classifier: Programming Language :: Python :: 2
Classifier: Programming Language :: Python :: 3
Classifier: License :: OSI Approved :: MIT License
Classifier: Operating System :: OS Independent
Requires-Python: >=2.7
License-File: LICENSE
Requires-Dist: click
Requires-Dist: click-log
Requires-Dist: watchdog
Requires-Dist: pyyaml
Requires-Dist: token-bucket
Requires-Dist: pyformance
